s3eval/1.py
s3eval/__init__.py
s3eval/convert_csv.py
s3eval/custom_template.py
s3eval/custom_template_parser.py
s3eval/general.py
s3eval/parser.py
s3eval/s3eval.py
s3eval/setup.py
s3eval/table_utils.py
s3eval/value_utils.py
s3eval/figs/__init__.py
s3eval/template/__init__.py
s3eval-0.3.0.dist-info/METADATA
s3eval-0.3.0.dist-info/WHEEL
s3eval-0.3.0.dist-info/top_level.txt
s3eval-0.3.0.dist-info/RECORD
