Metadata-Version: 2.1
Name: s3eval
Version: 0.3.0
Summary: S3Eval: A Synthetic, Scalable and Systematic Evaluation Suite for Language Models
Home-page: https://github.com/lfy79001/S3Eval
Author: Fangyu Lei
Author-email: leifangyu@qq.com
Classifier: Development Status :: 5 - Production/Stable
Classifier: License :: OSI Approved :: MIT License
Classifier: Programming Language :: Python :: 3
Classifier: Programming Language :: Python :: 3.7
Classifier: Programming Language :: Python :: 3.8
Classifier: Programming Language :: Python :: 3.9
Classifier: Programming Language :: Python :: 3.10
Requires-Dist: pandas
